Prac5_MQTZON001.sv
// Code your design here
module ALU(
    input clk,
  	input [7:0] A,B,
  	input [3:0] ALU_Sel,
  	output reg [7:0] ALU_out
);

  reg [7:0] ALU_result;

always@(posedge clk) //Triggered on rising edge clock
    begin
      	ALU_out = 8'b00000101;
        case(ALU_Sel)
            4'b0000:  //Manually enumerate Addition = 0000
                ALU_result = A + B;
            
            4'b0001:  //Manually enumerate Subtraction1 = 0001
                ALU_result = A - B;

            4'b0010:  //Manually enumerate multiplication = 0010
                ALU_result = A * B;
            
            4'b0011:  //Manually enumerate Division = 0011
                ALU_result = A / B;
          
          	4'b0100:  //Manually enumerate addA = 0100
                ALU_result += A;
          
          	4'b0101:  //Manually enumerate mulA = 0101
                ALU_result *= A;
          
          	4'b0110:  //Manually enumerate MAC = 0110
              	ALU_result += (A * B);
          
          	4'b0111:  //Manually enumerate ROL = 0111
              	ALU_result = {A[6:0],A[7:0]};
          
          	4'b1000:  //Manually enumerate ROR = 1000
              	ALU_result = {A[0],A[7:1]} ;
          
          	4'b1001:  //Manually enumerate AND = 1001
                ALU_result = A & B;
          
          	4'b1010:  //Manually enumerate OR = 1010
                ALU_result = A | B;
          
          	4'b1011:  //Manually enumerate XOR = 1011
                ALU_result = A ^ B;
          
          	4'b1100:  //Manually enumerate NAND = 1100
              	ALU_result = ~(A & B);
          
          	4'b1101:  //Manually enumerate ETH = 1101 with ternary
              	ALU_result = (A == B) ? 8'b11111111 :8'b00000000;
          
          	4'b1110:  //Manually enumerate GTH = 1110 with ternary
              	ALU_result = (A > B) ? 8'b11111111 :8'b00000000;
          
          	4'b1111:  //Manually enumerate LTH = 1111 with ternary
              	ALU_result = (A < B) ? 8'b11111111 :8'b00000000;
          
            default: ALU_result = A;
        endcase

        ALU_out <= ALU_result;
    end    
endmodule

Prac5_MQTZON001_tb.sv
// Code your testbench here
// or browse Examples
module ALU_tb();    
//inputs
reg clk; 
reg[7:0] A,B;
reg[3:0] ALU_Sel;
// output
wire [7:0] ALU_Out; 
//Instantiate the design under test
integer index;
ALU dut(
    .clk(clk),
    .A(A),
    .B(B),
    .ALU_Sel(ALU_Sel),
    .ALU_out(ALU_Out));

initial begin //Initial means this only happens once
    $display("A  B  ALU_Sel  ALU_Out");
    $monitor("%b  %b  %b     %b",A,B,ALU_Sel,ALU_Out);
  	$dumpfile("dump.vcd");
	$dumpvars;
    clk = 1'b1;
    A = 8'b10110001;
    B = 8'b00100000;
    ALU_Sel = 4'b0000;
  
  for(index = 0; index < 15; index++)
    begin
      #5
      ALU_Sel += 4'b0001;
      clk = !clk;
      #5
      clk = !clk;
    end
//     #5  //Note: This is not synthesizable and only available in simulation
//         clk=!clk;
//     #5
//         clk=!clk;
//         ALU_Sel = 2'b01;
//     #5
//         clk=!clk;
//     #5
//         clk=!clk;
//         ALU_Sel = 2'b10;
//     #5
//         clk=!clk;
//     #5
//         clk=!clk;
//         ALU_Sel = 2'b11;
//     #5
//         clk = !clk;
    end
endmodule

dump.vcd
$date
	Sun Oct 17 21:23:22 2021
$end
$version
	Icarus Verilog
$end
$timescale
	1s
$end
$scope module ALU_tb $end
$var wire 8 ! ALU_Out [7:0] $end
$var reg 8 " A [7:0] $end
$var reg 4 # ALU_Sel [3:0] $end
$var reg 8 $ B [7:0] $end
$var reg 1 % clk $end
$var integer 32 & index [31:0] $end
$scope module dut $end
$var wire 8 ' A [7:0] $end
$var wire 4 ( ALU_Sel [3:0] $end
$var wire 8 ) B [7:0] $end
$var wire 1 % clk $end
$var reg 8 * ALU_out [7:0] $end
$var reg 8 + ALU_result [7:0] $end
$upscope $end
$upscope $end
$enddefinitions $end
#0
$dumpvars
b11010001 +
b11010001 *
b100000 )
b0 (
b10110001 '
b0 &
1%
b100000 $
b0 #
b10110001 "
b11010001 !
$end
#5
0%
b1 #
b1 (
#10
b10010001 +
b10010001 !
b10010001 *
b1 &
1%
#15
0%
b10 #
b10 (
#20
b100000 +
b100000 !
b100000 *
b10 &
1%
#25
0%
b11 #
b11 (
#30
b101 +
b101 !
b101 *
b11 &
1%
#35
0%
b100 #
b100 (
#40
b10110110 !
b10110110 *
b10110110 +
b100 &
1%
#45
0%
b101 #
b101 (
#50
b11010110 +
b11010110 !
b11010110 *
b101 &
1%
#55
0%
b110 #
b110 (
#60
b11110110 +
b11110110 !
b11110110 *
b110 &
1%
#65
0%
b111 #
b111 (
#70
b10110001 +
b10110001 !
b10110001 *
b111 &
1%
#75
0%
b1000 #
b1000 (
#80
b11011000 +
b11011000 !
b11011000 *
b1000 &
1%
#85
0%
b1001 #
b1001 (
#90
b100000 +
b100000 !
b100000 *
b1001 &
1%
#95
0%
b1010 #
b1010 (
#100
b10110001 +
b10110001 !
b10110001 *
b1010 &
1%
#105
0%
b1011 #
b1011 (
#110
b10010001 +
b10010001 !
b10010001 *
b1011 &
1%
#115
0%
b1100 #
b1100 (
#120
b11011111 +
b11011111 !
b11011111 *
b1100 &
1%
#125
0%
b1101 #
b1101 (
#130
b0 +
b0 !
b0 *
b1101 &
1%
#135
0%
b1110 #
b1110 (
#140
b11111111 +
b11111111 !
b11111111 *
b1110 &
1%
#145
0%
b1111 #
b1111 (
#150
b0 +
b0 !
b0 *
b1111 &
1%
